RedisShujukuXuexiJiaochengCYuyanBianchengWangFix1/README.md
RedisShujukuXuexiJiaochengCYuyanBianchengWangFix1/__init__.py
RedisShujukuXuexiJiaochengCYuyanBianchengWangFix1/__main__.py
RedisShujukuXuexiJiaochengCYuyanBianchengWangFix1/file.epub
RedisShujukuXuexiJiaochengCYuyanBianchengWangFix1/index.html
RedisShujukuXuexiJiaochengCYuyanBianchengWangFix1/css/__init__.py
RedisShujukuXuexiJiaochengCYuyanBianchengWangFix1/css/annotations.css
RedisShujukuXuexiJiaochengCYuyanBianchengWangFix1/css/main.css
RedisShujukuXuexiJiaochengCYuyanBianchengWangFix1/css/normalize.css
RedisShujukuXuexiJiaochengCYuyanBianchengWangFix1/css/popup.css
RedisShujukuXuexiJiaochengCYuyanBianchengWangFix1/font/__init__.py
RedisShujukuXuexiJiaochengCYuyanBianchengWangFix1/font/fontello.eot
RedisShujukuXuexiJiaochengCYuyanBianchengWangFix1/font/fontello.svg
RedisShujukuXuexiJiaochengCYuyanBianchengWangFix1/font/fontello.ttf
RedisShujukuXuexiJiaochengCYuyanBianchengWangFix1/font/fontello.woff
RedisShujukuXuexiJiaochengCYuyanBianchengWangFix1/img/__init__.py
RedisShujukuXuexiJiaochengCYuyanBianchengWangFix1/img/annotator-glyph-sprite.png
RedisShujukuXuexiJiaochengCYuyanBianchengWangFix1/img/annotator-icon-sprite.png
RedisShujukuXuexiJiaochengCYuyanBianchengWangFix1/img/apple-touch-icon.png
RedisShujukuXuexiJiaochengCYuyanBianchengWangFix1/img/cancelfullscreen.png
RedisShujukuXuexiJiaochengCYuyanBianchengWangFix1/img/close.png
RedisShujukuXuexiJiaochengCYuyanBianchengWangFix1/img/fullscreen.png
RedisShujukuXuexiJiaochengCYuyanBianchengWangFix1/img/loader.gif
RedisShujukuXuexiJiaochengCYuyanBianchengWangFix1/img/menu-icon.png
RedisShujukuXuexiJiaochengCYuyanBianchengWangFix1/img/save.png
RedisShujukuXuexiJiaochengCYuyanBianchengWangFix1/img/saved.png
RedisShujukuXuexiJiaochengCYuyanBianchengWangFix1/img/settings-s.png
RedisShujukuXuexiJiaochengCYuyanBianchengWangFix1/img/settings.png
RedisShujukuXuexiJiaochengCYuyanBianchengWangFix1/img/star.png
redis_shujuku_xuexi_jiaocheng_c_yuyan_biancheng_wang_fix1-2025.3.24.0.dist-info/METADATA
redis_shujuku_xuexi_jiaocheng_c_yuyan_biancheng_wang_fix1-2025.3.24.0.dist-info/WHEEL
redis_shujuku_xuexi_jiaocheng_c_yuyan_biancheng_wang_fix1-2025.3.24.0.dist-info/entry_points.txt
redis_shujuku_xuexi_jiaocheng_c_yuyan_biancheng_wang_fix1-2025.3.24.0.dist-info/top_level.txt
redis_shujuku_xuexi_jiaocheng_c_yuyan_biancheng_wang_fix1-2025.3.24.0.dist-info/RECORD
